OpenAccess/__init__.py
OpenAccess/openaccess.py
OpenAccess-0.4.dist-info/METADATA
OpenAccess-0.4.dist-info/WHEEL
OpenAccess-0.4.dist-info/top_level.txt
OpenAccess-0.4.dist-info/RECORD
