Metadata-Version: 2.1
Name: OpenAccess
Version: 0.4
Summary: Librería no oficial para leer comunicarse con un servidor de LENEL OpenAccess 
Home-page: https://github.com/alejomejia1
Author: Alejandro Mejia Ayala, Jaiber Camacho
Author-email: alejandromejia@qaingenieros.com
License: GNU
Requires-Dist: requests
